irtkit/__init__.py
irtkit-0.1.0.dist-info/LICENSE
irtkit-0.1.0.dist-info/METADATA
irtkit-0.1.0.dist-info/WHEEL
irtkit-0.1.0.dist-info/RECORD
