Metadata-Version: 2.1
Name: irtkit
Version: 0.1.0
Summary: Item Response Theory in Python
License: MIT
Author: Ivan Guilhon
Author-email: ivanguilhonn@gmail.com
Requires-Python: >=3.12,<4.0
Classifier: License :: OSI Approved :: MIT License
Classifier: Programming Language :: Python :: 3
Classifier: Programming Language :: Python :: 3.12
Classifier: Programming Language :: Python :: 3.13
Requires-Dist: matplotlib (>=3.10.0,<4.0.0)
Requires-Dist: numpy (>=2.2.1,<3.0.0)
Requires-Dist: pandas (>=2.2.3,<3.0.0)
Requires-Dist: scipy (>=1.14.1,<2.0.0)
